{"data":{"head":{"itype":8,"data":{"id":"2103266","title":"Khoobsurat","type":21,"image":"https://images1.hungama.com/tr:n-a_11_xs:n-a_webp/c/1/2d4/a8f/2103266/2103266_800x800.jpg","playble_image":"https://images1.hungama.com/tr:n-a_11_l:n-a_webp/c/1/2d4/a8f/2103266/2103266_800x800.jpg","releasedate":"2005/01/07 00:00:00","genre":["Bollywood"],"category":[],"subgenre_name":[],"subtitle":"Udit Narayan","duration":326,"misc":{"cast":"","explicit":0,"pid":[1120350,42905356,48264943,26566780,26566788,31360218,32296342,46688283,50483863,51879640,60672730,62443240,78697127],"p_name":["Rog","Best Collections - Udit Narayan","Saregama Music Carnival Vol.2","Ek Cup Cheeni","Ek Cup Compliments","Romantic Era - Udit Narayan","Musical Delight - Udit Narayan Hits","Pyar Ke Pal","The Best of Udit Narayan","Jadu Hai Nasha Hai","Pyar Ki Kashti Mein - Udit Narayan Spl","Kaho Naa Pyar Hai - Valentine Hits","The Golden Voice … Udit Narayan"],"keywords":["Bollywood","Audio","Rog","Khoobsurat #"],"rating_critic":0,"rating_user":0,"movierights":[],"attribute_censor_rating":[],"nudity":"0","playcount":953815,"s_artist":["Udit Narayan","M. M. Kreem","Irrfan Khan","Neelesh Misra","Pooja Bhatt"],"artist":["Udit Narayan","M. M. Kreem","Irrfan Khan","Neelesh Misra","Pooja Bhatt"],"actorf":["Irrfan Khan"],"lyricistf":["Neelesh Misra"],"musicdirectorf":["M. M. Kreem"],"singerf":["Udit Narayan"],"lyricist":["Neelesh Misra"],"mood":"","tempo":[],"sl":{"lyric":{"link":"https://images.hungama.com/c/9/2d4/a8f/2103266/2103266_lyrics-eng.lrc","lang_id":2103266,"lang":"eng"}},"fav_count":5196,"f_fav_count":"5,196","synopsis":"","lang":["Hindi"],"url":"","dl":"","urls":[],"share":"https://www.hungama.com/song/khoobsurat/2103266//https://images1.hungama.com/tr:n-a_11_xs:n-a_webp/c/1/2d4/a8f/2103266/2103266_800x800.jpg/","description":"","vendorid":271,"vendor":"Saregama India Ltd","count_era_from":"","count_era_to":"","skipIntro":{"skipCreditET":0,"skipCreditST":0,"skipIntroET":0,"skipIntroST":0}}}},"body":{"data":{"url":{"playable":[{"identifier":"playableURL","key":"auto","protocol":"hls","fileSubTypeId":1235,"data":"https://media.hungama.com/c/4/2d4/a8f/2103266/2103266_,96,128,192,.mp4.m3u8?QQtIrtP5I7bxDyz5FkHmYCe0EMGOnxue6t2XyICkiMQ6HcnfkjBJnqUuDyw93IN044kRvGO72loPiE3jYoschV9Hr0lme6rNCbzOdaPevAka-zpbGosrYOwC-A"},{"identifier":"playableURL","key":"low","protocol":"mp3","fileSubTypeId":250,"data":"https://media.hungama.com/c/4/2d4/a8f/2103266/2103266_32.mp3?pf-wsscV1G1KpFZCb2Kg_5ZrJxHeitHJX0ySw-_FftEzjxTCExrizEc5q02Mhtf4nXQNpdMkEPU3DW00pvdJ94B7lE-mCmPqSVW0on21byyX9XcwRBQl8697GoxGU1ycCw"},{"identifier":"playableURL","key":"mid","protocol":"mp3","fileSubTypeId":355,"data":"https://media.hungama.com/c/4/2d4/a8f/2103266/2103266_64.mp3?bb228i1tgZLQ09c2zPHPYsdsyk_yoQpBgwQwfugkoVntzTf6_XBlq01Ha2usSaRRCNckiCmj2Eb8FTuWaZzmgperqejpuZPAto88-tsS3taGarrU98roCRLvR6mjK3ptNw"},{"identifier":"playableURL","key":"high","protocol":"mp3","fileSubTypeId":8,"data":"https://media.hungama.com/c/4/2d4/a8f/2103266/2103266_128.mp3?GxTDeYCSZLpLX-T9YF4WAeFB9e-Thm_r1qN6PxhH7RRvx3ZcH1NjbmSzbZwmkt8xOMsu7cTMcXej0aRo0TOtNHlOFEEBa3bCJ_vQ1d2IM_w2gpbR7jZ5IQyfp1-zdZGpeZo"},{"identifier":"playableURL","key":"hd","protocol":"mp3","fileSubTypeId":763,"data":"https://media.hungama.com/c/4/2d4/a8f/2103266/2103266_320.mp3?HxSwwoqAF7tZSafIrEjNGVYLNeTq8Ti7ZZkQSzaCDYUg01grTiF452f2h-KjhMZOOOMaIvfP3VZvpIZhxQioaqXEDfNZr9n2dUfsOOJCIBtBZ-F1F_Ec7I7VI16mMRLCXoI"}]}}}}}